Topsis/102103615.py
Topsis/__init__.py
Topsis_Chaitanya_102103615-1.0.0.dist-info/METADATA
Topsis_Chaitanya_102103615-1.0.0.dist-info/WHEEL
Topsis_Chaitanya_102103615-1.0.0.dist-info/entry_points.txt
Topsis_Chaitanya_102103615-1.0.0.dist-info/top_level.txt
Topsis_Chaitanya_102103615-1.0.0.dist-info/RECORD
