Metadata-Version: 2.1
Name: Topsis-Chaitanya-102103615
Version: 1.0.0
Summary: Topsis
Home-page: https://github.com/CHAITANYA2605/Topsis_implementation
Author: Chaitanya Arora
Author-email: chaitanyaarora26@gmail.com
License: MIT
Classifier: License :: OSI Approved :: MIT License
Classifier: Programming Language :: Python :: 3.6
Classifier: Programming Language :: Python :: 3.7
Classifier: Programming Language :: Python :: 3.8
